ColorfulConsole/CColor.py
ColorfulConsole/CConsole.py
ColorfulConsole/CError.py
ColorfulConsole/__init__.py
r_colorfulconsole-0.1.0.dist-info/METADATA
r_colorfulconsole-0.1.0.dist-info/WHEEL
r_colorfulconsole-0.1.0.dist-info/top_level.txt
r_colorfulconsole-0.1.0.dist-info/RECORD
