Metadata-Version: 2.1
Name: r-colorfulconsole
Version: 0.1.0
Summary: A tool that can make your console output colorful.
Author: R.
Author-email: 3228097751@qq.com
Classifier: Programming Language :: Python :: 3
Classifier: License :: OSI Approved :: MIT License
Classifier: Operating System :: OS Independent
